srim/executor/__init__.py
srim/executor/docker.py
srim/executor/executor.py
srim/executor/native.py
srim/executor/types.py
pysrim_executor-0.1.0.dist-info/LICENSE
pysrim_executor-0.1.0.dist-info/WHEEL
pysrim_executor-0.1.0.dist-info/METADATA
pysrim_executor-0.1.0.dist-info/RECORD
