Metadata-Version: 2.1
Name: pysrim-executor
Version: 0.1.0
Summary: Abstracted executor for PySRIM
Home-page: https://github.com/agoose77/pysrim-executor
License: MIT
Author: Angus Hollands
Author-email: goosey15@gmail.com
Requires-Python: >=3.6,<4.0
Classifier: License :: OSI Approved :: MIT License
Classifier: Programming Language :: Python :: 3
Classifier: Programming Language :: Python :: 3.6
Classifier: Programming Language :: Python :: 3.7
Classifier: Programming Language :: Python :: 3.8
Classifier: Programming Language :: Python :: 3.9
Requires-Dist: pysrim (>=0.5.10,<0.6.0)
Project-URL: Repository, https://github.com/agoose77/pysrim-executor
